znvs/__init__.py
znvs/ate.py
znvs/decoder.py
znvs/encoder.py
znvs/entry.py
znvs/exception.py
znvs/nvs.py
znvs/sector.py
znvs/util.py
znvs-0.1.0.dist-info/LICENSE
znvs-0.1.0.dist-info/METADATA
znvs-0.1.0.dist-info/WHEEL
znvs-0.1.0.dist-info/top_level.txt
znvs-0.1.0.dist-info/RECORD
