Metadata-Version: 2.1
Name: znvs
Version: 0.1.0
Summary: Tool to encode and decode Zephyrproject NVS filesystem.
Author: Piotr Ciura
License: MIT
Project-URL: Homepage, https://github.com/ptrcr/znvs
Classifier: Programming Language :: Python :: 3
Classifier: License :: OSI Approved :: MIT License
Classifier: Operating System :: OS Independent
Requires-Python: >=3.10
License-File: LICENSE
Requires-Dist: crc ~=6.1
Provides-Extra: dev
Requires-Dist: PyYAML ~=6.0 ; extra == 'dev'
Requires-Dist: pytest ~=7.2 ; extra == 'dev'
